wacom_profile/__init__.py
wacom_profile/wacom_profile.py
wacom_profile-0.1.0.dist-info/METADATA
wacom_profile-0.1.0.dist-info/WHEEL
wacom_profile-0.1.0.dist-info/entry_points.txt
wacom_profile-0.1.0.dist-info/top_level.txt
wacom_profile-0.1.0.dist-info/RECORD
