Metadata-Version: 2.1
Name: wacom-profile
Version: 0.1.0
Summary: Wacom Intuos tablet command mapping.
Author: Aaron Segura
License: License :: OSI Approved :: GNU General Public License v3 (GPLv3)
Project-URL: Homepage, https://github.com/aaronsegura/wacom_profile
Project-URL: Bug Tracker, https://github.com/aaronsegura/wacom_profile/issues
Keywords: wacom,intuos
Classifier: Development Status :: 4 - Beta
Classifier: Framework :: Flake8
Classifier: Intended Audience :: End Users/Desktop
Classifier: License :: OSI Approved :: GNU General Public License v3 (GPLv3)
Classifier: Natural Language :: English
Classifier: Programming Language :: Python :: 3.5
Requires-Python: >=3.5
